pvops/__init__.py
pvops/iv/__init__.py
pvops/iv/extractor.py
pvops/iv/physics_utils.py
pvops/iv/preprocess.py
pvops/iv/simulator.py
pvops/iv/timeseries_simulator.py
pvops/iv/utils.py
pvops/iv/models/__init__.py
pvops/iv/models/nn.py
pvops/text/__init__.py
pvops/text/classify.py
pvops/text/defaults.py
pvops/text/nlp_utils.py
pvops/text/preprocess.py
pvops/text/utils.py
pvops/text/visualize.py
pvops/text2time/__init__.py
pvops/text2time/preprocess.py
pvops/text2time/utils.py
pvops/text2time/visualize.py
pvops/timeseries/__init__.py
pvops/timeseries/preprocess.py
pvops/timeseries/models/AIT.py
pvops/timeseries/models/__init__.py
pvops/timeseries/models/iec.py
pvops/timeseries/models/linear.py
pvops/timeseries/models/survival.py
pvops-0.7.0.dist-info/licenses/LICENSE
tutorials/__init__.py
pvops-0.7.0.dist-info/METADATA
pvops-0.7.0.dist-info/WHEEL
pvops-0.7.0.dist-info/top_level.txt
pvops-0.7.0.dist-info/RECORD
